advancedcipher/cipher.py
advancedcipher_lib-1.0.0.dist-info/METADATA
advancedcipher_lib-1.0.0.dist-info/WHEEL
advancedcipher_lib-1.0.0.dist-info/top_level.txt
advancedcipher_lib-1.0.0.dist-info/RECORD
