Metadata-Version: 2.4
Name: advancedcipher_lib
Version: 1.0.0
Summary: Advanced encryption and decryption library with multiple cipher algorithms
Author: Ali Alsheikh
Author-email: Ali Alsheikh <ali453345ali@gmail.com>
License: MIT
Project-URL: Homepage, https://github.com/allmyprojects12/AdvancedCipherLib
Project-URL: Bug Tracker, https://github.com/allmyprojects12/AdvancedCipherLib/issues
Classifier: Programming Language :: Python :: 3
Classifier: License :: OSI Approved :: MIT License
Classifier: Operating System :: OS Independent
Requires-Python: >=3.6
Dynamic: author
Dynamic: requires-python
